{
	"BannerImg":[
		{
			"info":"真希波,凌波丽,明日香  《福音战士新剧场版》",
			"url" :"https://cdn.jsdelivr.net/gh/lgzzk1024/lgzzk@main/EVA.jpg" 
		},
		{
			"info":"Bite my shiny metal ass 《飞出个未来》",
			"url" :"https://cdn.jsdelivr.net/gh/lgzzk1024/lgzzk@main/bd.jpg"
		},
		{
			"info":"Kikyou《犬夜叉》",
			"url" :"https://cdn.jsdelivr.net/gh/lgzzk1024/lgzzk@main/jg.jpg"
		},
		{
			"info": "02《DARLING in the FRANXX》",
			"url" :"https://cdn.jsdelivr.net/gh/lgzzk1024/lgzzk@main/02.jpg"
		},
		{
			"info": "明日香·兰格雷 (新世纪福音战士)",
			"url" :"https://cdn.jsdelivr.net/gh/lgzzk1024/lgzzk@main/mrx.jpg"
		},
		{
			"info":"三澄美琴 《非自然死亡》",
			"url" :"https://cdn.jsdelivr.net/gh/lgzzk1024/lgzzk@main/sylm_Q.jpg"
		},
		{
			"info":"saber,亚瑟王,阿尔托莉雅·潘德拉贡 (Fate/stay night 06版)",
			"url":"https://cdn.jsdelivr.net/gh/lgzzk1024/lgzzk@main/saber.jpg"
		},
		{
			"info":"蒸汽波(Vaporwave 风格)",
			"url" :"https://cdn.jsdelivr.net/gh/lgzzk1024/lgzzk@main/steam.jpg"
		},
		{
			"info":"薇尔莉特·伊芙加登《紫罗兰永恒花园》",
			"url" :"https://cdn.jsdelivr.net/gh/lgzzk1024/lgzzk@main/wertl.jpg"
		},
		{
			"info":"《瑞克和莫蒂》《飞出个未来》......",
			"url" :"https://cdn.jsdelivr.net/gh/lgzzk1024/lgzzk@main/mingle.jpg"
		},
		{
			"info":"石原里美 《非自然死亡》",
			"url" :"https://cdn.jsdelivr.net/gh/lgzzk1024/lgzzk@main/sylm.jpeg"

		},
		{
			"info":"saber,亚瑟王,阿尔托莉雅·潘德拉贡《fate》",
			"url" :"https://cdn.jsdelivr.net/gh/lgzzk1024/lgzzk@main/saber1.jpg"
		},
		{
			"info":"saber,亚瑟王,阿尔托莉雅·潘德拉贡《fate》",
			"url" :"https://cdn.jsdelivr.net/gh/lgzzk1024/lgzzk@main/saber2.png"
		},
		{
			"info":"saber,亚瑟王,阿尔托莉雅·潘德拉贡《fate》",
			"url" :"https://cdn.jsdelivr.net/gh/lgzzk1024/lgzzk@main/saber4.jpg"
		},
		{
			"info":"《願い~あの頃のキミへ~》  當山みれい",
			"url" :"https://cdn.jsdelivr.net/gh/lgzzk1024/lgzzk@main/dszl.jpg"
		}
	],
	"childhood":"https://lgzzk-1304498835.cos.ap-shanghai.myqcloud.com/childhood.jpg",
	"childhood1":"https://lgzzk-1304498835.cos.ap-shanghai.myqcloud.com/childhood.jpg"
}